gufo/traceroute/__init__.py
gufo/traceroute/bpf.py
gufo/traceroute/bpffilter.py
gufo/traceroute/py.typed
gufo/traceroute/traceroute.py
gufo/traceroute/whois.py
gufo_traceroute-0.2.1.dist-info/licenses/LICENSE.md
gufo_traceroute-0.2.1.dist-info/METADATA
gufo_traceroute-0.2.1.dist-info/WHEEL
gufo_traceroute-0.2.1.dist-info/top_level.txt
gufo_traceroute-0.2.1.dist-info/zip-safe
gufo_traceroute-0.2.1.dist-info/RECORD
