Metadata-Version: 2.4
Name: gufo_traceroute
Version: 0.2.1
Author: Gufo Labs
License: BSD 3-Clause License
Project-URL: Bug Tracker, https://github.com/gufolabs/gufo_traceroute/issues
Project-URL: Changelog, https://github.com/gufolabs/gufo_traceroute/blob/master/CHANGELOG.md
Project-URL: Documentation, https://docs.gufolabs.com/gufo_traceroute/
Project-URL: Homepage, https://github.com/gufolabs/gufo_traceroute/
Project-URL: Source Code, https://github.com/gufolabs/gufo_traceroute/
Keywords: traceroute,plugin
Classifier: Development Status :: 5 - Production/Stable
Classifier: Intended Audience :: Developers
Classifier: Intended Audience :: System Administrators
Classifier: Intended Audience :: Telecommunications Industry
Classifier: Programming Language :: Python :: 3.9
Classifier: Programming Language :: Python :: 3.10
Classifier: Programming Language :: Python :: 3.11
Classifier: Programming Language :: Python :: 3.12
Classifier: Programming Language :: Python :: 3.13
Classifier: License :: OSI Approved :: BSD License
Classifier: Topic :: Software Development
Classifier: Topic :: Software Development :: Libraries
Classifier: Topic :: Software Development :: Libraries :: Python Modules
Classifier: Operating System :: OS Independent
Classifier: Typing :: Typed
Requires-Python: >=3.9
License-File: LICENSE.md
Dynamic: license-file
